<?xml version="1.0" encoding="UTF-8" ?>
<pageDefinition xmlns="http://xmlns.oracle.com/adfm/uimodel"
                version="11.1.1.56.60" id="g_memcvrclmPageDef"
                Package="view.pageDefs">
  <parameters/>
  <executables>
    <variableIterator id="variables"/>
    <methodIterator Binds="findProducts.result" DataControl="ProductsDAO"
                    RangeSize="25"
                    BeanClass="LMSG.view.GroupProducts.productDetails"
                    id="findProductsIterator"/>
    <searchRegion Binds="findProductsIterator" Criteria=""
                  Customizer="oracle.jbo.uicli.binding.JUSearchBindingCustomizer"
                  id="productDetailsQuery"/>
    <methodIterator Binds="FindPolicyProposers.result" DataControl="policiesDAO"
                    RangeSize="25" BeanClass="LMSG.view.Policy.policies"
                    id="FindPolicyProposersIterator"/>
    <searchRegion Binds="FindPolicyProposersIterator" Criteria=""
                  Customizer="oracle.jbo.uicli.binding.JUSearchBindingCustomizer"
                  id="policiesQuery"/>
 <methodIterator Binds="FindPolicies.result" DataControl="policiesDAO"
                    RangeSize="25" BeanClass="LMSG.view.Policy.policies"
                    id="FindPoliciesIterator"/>
  </executables>
  <bindings>
    <methodAction id="findProducts" RequiresUpdateModel="true"
                  Action="invokeMethod" MethodName="findProducts"
                  IsViewObjectMethod="false" DataControl="ProductsDAO"
                  InstanceName="ProductsDAO.dataProvider"
                  ReturnName="ProductsDAO.methodResults.findProducts_ProductsDAO_dataProvider_findProducts_result"/>
    <tree IterBinding="findProductsIterator" id="productDetails">
      <nodeDefinition DefName="LMSG.view.GroupProducts.productDetails"
                      Name="productDetails0">
        <AttrNames>
          <Item Value="prodCode"/>
          <Item Value="prodDesc"/>
          <Item Value="prodshtDesc"/>
        </AttrNames>
      </nodeDefinition>
    </tree>
    <methodAction id="FindPolicyProposers" RequiresUpdateModel="true"
                  Action="invokeMethod" MethodName="FindPolicyProposers"
                  IsViewObjectMethod="false" DataControl="policiesDAO"
                  InstanceName="policiesDAO.dataProvider"
                  ReturnName="policiesDAO.methodResults.FindPolicyProposers_policiesDAO_dataProvider_FindPolicyProposers_result"/>
    <tree IterBinding="FindPolicyProposersIterator" id="policies">
      <nodeDefinition DefName="LMSG.view.Policy.policies" Name="policies0">
        <AttrNames>
          <Item Value="POL_CODE"/>
          <Item Value="CLIENT_DISPLAY"/>
          <Item Value="POL_POLICY_NO"/>
        </AttrNames>
      </nodeDefinition>
    </tree>
    <methodAction id="FindPolicies" RequiresUpdateModel="true"
                  Action="invokeMethod" MethodName="FindPolicies"
                  IsViewObjectMethod="false" DataControl="policiesDAO"
                  InstanceName="policiesDAO.dataProvider"
                  ReturnName="policiesDAO.methodResults.FindPolicies_policiesDAO_dataProvider_FindPolicies_result"/>
     <attributeValues IterBinding="FindPoliciesIterator" id="POL_POLICY_NO">
      <AttrNames>
        <Item Value="POL_POLICY_NO"/>
      </AttrNames>
    </attributeValues>
    <attributeValues IterBinding="FindPoliciesIterator" id="CLIENT_DISPLAY">
      <AttrNames>
        <Item Value="CLIENT_DISPLAY"/>
      </AttrNames>
    </attributeValues> 
    <attributeValues IterBinding="FindPoliciesIterator" id="PRO_DESC">
      <AttrNames>
        <Item Value="PRO_DESC"/>
      </AttrNames>
    </attributeValues>
    <attributeValues IterBinding="FindPoliciesIterator" id="BRANCH_DISPLAY">
      <AttrNames>
        <Item Value="BRANCH_DISPLAY"/>
      </AttrNames>
    </attributeValues>
    <attributeValues IterBinding="FindPoliciesIterator"
                     id="pol_freq_of_payment_disp">
      <AttrNames>
        <Item Value="pol_freq_of_payment_disp"/>
      </AttrNames>
    </attributeValues>
    <attributeValues IterBinding="FindPoliciesIterator" id="POL_EFFECTIVE_DATE">
      <AttrNames>
        <Item Value="POL_EFFECTIVE_DATE"/>
      </AttrNames>
    </attributeValues>
    <attributeValues IterBinding="FindPoliciesIterator"
                     id="pol_dependt_covered_disp">
      <AttrNames>
        <Item Value="pol_dependt_covered_disp"/>
      </AttrNames>
    </attributeValues>
    <attributeValues IterBinding="FindPoliciesIterator" id="pol_status_disp">
      <AttrNames>
        <Item Value="pol_status_disp"/>
      </AttrNames>
    </attributeValues>
    <attributeValues IterBinding="FindPoliciesIterator" id="UW_YEAR">
      <AttrNames>
        <Item Value="UW_YEAR"/>
      </AttrNames>
    </attributeValues>
     <attributeValues IterBinding="FindPoliciesIterator" id="OCCUPATION_DISPLAY">
      <AttrNames>
        <Item Value="OCCUPATION_DISPLAY"/>
      </AttrNames>
    </attributeValues>
    <attributeValues IterBinding="FindPoliciesIterator" id="POL_INCEPTION_DATE">
      <AttrNames>
        <Item Value="POL_INCEPTION_DATE"/>
      </AttrNames>
    </attributeValues>
     <attributeValues IterBinding="FindPoliciesIterator" id="LPAG_DESC">
      <AttrNames>
        <Item Value="LPAG_DESC"/>
      </AttrNames>
    </attributeValues>
    <attributeValues IterBinding="FindPoliciesIterator" id="POL_UMBRELLADESC">
      <AttrNames>
        <Item Value="POL_UMBRELLADESC"/>
      </AttrNames>
    </attributeValues>
     <attributeValues IterBinding="FindPoliciesIterator"
                     id="pol_pens_category_disp">
      <AttrNames>
        <Item Value="pol_pens_category_disp"/>
      </AttrNames>
    </attributeValues>
    <attributeValues IterBinding="FindPoliciesIterator"
                     id="pol_savings_rider_disp">
      <AttrNames>
        <Item Value="pol_savings_rider_disp"/>
      </AttrNames>
    </attributeValues>
     <attributeValues IterBinding="FindPoliciesIterator"
                     id="pol_os_loan_calc_disp">
      <AttrNames>
        <Item Value="pol_os_loan_calc_disp"/>
      </AttrNames>
    </attributeValues>
  </bindings>
</pageDefinition>
